afdiankit/__init__.py
afdiankit/afdian.py
afdiankit/auth/__init__.py
afdiankit/auth/base.py
afdiankit/auth/token.py
afdiankit/auth/unauth.py
afdiankit/config.py
afdiankit/core.py
afdiankit/exception.py
afdiankit/open/__init__.py
afdiankit/open/types.py
afdiankit/open/utils.py
afdiankit/py.typed
afdiankit/response.py
afdiankit/rest/__init__.py
afdiankit/rest/account.py
afdiankit/rest/badge.py
afdiankit/rest/bang.py
afdiankit/rest/category.py
afdiankit/rest/comment.py
afdiankit/rest/creator.py
afdiankit/rest/faq.py
afdiankit/rest/init.py
afdiankit/rest/log.py
afdiankit/rest/message.py
afdiankit/rest/my.py
afdiankit/rest/oauth.py
afdiankit/rest/oauth2.py
afdiankit/rest/order.py
afdiankit/rest/passport.py
afdiankit/rest/paypal.py
afdiankit/rest/post.py
afdiankit/rest/suiyinzi.py
afdiankit/rest/types.py
afdiankit/rest/upload.py
afdiankit/rest/user.py
afdiankit/rest/welcome.py
afdiankit/typing.py
afdiankit/utils.py
afdiankit-0.2.0.dist-info/LICENSE
afdiankit-0.2.0.dist-info/METADATA
afdiankit-0.2.0.dist-info/WHEEL
afdiankit-0.2.0.dist-info/RECORD
