Metadata-Version: 2.1
Name: afdiankit
Version: 0.2.0
Summary: Afdian SDK for Python
Home-page: https://github.com/StarHeartHunt/afdiankit
License: MIT
Keywords: afdian
Author: StarHeartHunt
Author-email: starheart233@gmail.com
Requires-Python: >=3.8,<4.0
Classifier: License :: OSI Approved :: MIT License
Classifier: Programming Language :: Python :: 3
Classifier: Programming Language :: Python :: 3.8
Classifier: Programming Language :: Python :: 3.9
Classifier: Programming Language :: Python :: 3.10
Classifier: Programming Language :: Python :: 3.11
Requires-Dist: anyio (>=3.6.1,<4.0.0)
Requires-Dist: httpx (>=0.23.0,<1.0.0)
Requires-Dist: pydantic (>=2.0.0,<3.0.0)
Requires-Dist: typing-extensions (>=4.3.0,<5.0.0)
Project-URL: Documentation, https://github.com/StarHeartHunt/afdiankit
Project-URL: Repository, https://github.com/StarHeartHunt/afdiankit
